graphql_framework/__init__.py
graphql_framework/converter.py
graphql_framework/decorators.py
graphql_framework/fields.py
graphql_framework/mixins.py
graphql_framework/schema.py
graphql_framework/templates/graphql_framework/graphiql.html
graphql_framework/urls.py
graphql_framework/views.py
django_gql_framework-0.1.13.dist-info/WHEEL
django_gql_framework-0.1.13.dist-info/METADATA
django_gql_framework-0.1.13.dist-info/RECORD
