Metadata-Version: 2.1
Name: django-gql-framework
Version: 0.1.13
Summary: 
License: MIT
Author: Ellis Percival
Author-email: flyte@failcode.co.uk
Requires-Python: >=3.7,<4.0
Classifier: License :: OSI Approved :: MIT License
Classifier: Programming Language :: Python :: 3
Classifier: Programming Language :: Python :: 3.7
Classifier: Programming Language :: Python :: 3.8
Requires-Dist: django-guardian (>=2.3.0,<3.0.0)
Requires-Dist: graphql-core (>=3)
